autoshell/__init__.py
autoshell/__main__.py
autoshell/__version__.py
autoshell/cisco/__init__.py
autoshell/cisco/neighbors/__init__.py
autoshell/cisco/neighbors/handlers.py
autoshell/cisco/neighbors/cli/__init__.py
autoshell/cisco/neighbors/cli/scrapers.py
autoshell/common/__init__.py
autoshell/common/autoqueue.py
autoshell/common/credentials.py
autoshell/common/expressions.py
autoshell/common/hosts.py
autoshell/common/neighbors.py
autoshell/connectors/__init__.py
autoshell/connectors/cli.py
autoshell/hp/__init__.py
autoshell/hp/neighbors/__init__.py
autoshell/hp/neighbors/handlers.py
autoshell/hp/neighbors/cli/__init__.py
autoshell/hp/neighbors/cli/scrapers.py
autoshell/modules/__init__.py
autoshell/modules/cmd.py
autoshell/modules/crawl.py
autoshell/modules/neighbors.py
autoshell-0.0.46.dist-info/LICENSE
autoshell-0.0.46.dist-info/METADATA
autoshell-0.0.46.dist-info/WHEEL
autoshell-0.0.46.dist-info/entry_points.txt
autoshell-0.0.46.dist-info/top_level.txt
autoshell-0.0.46.dist-info/RECORD
