Metadata-Version: 2.1
Name: autoshell
Version: 0.0.46
Summary: Simple, fully programmable, shell-based network automation utility
Home-page: https://github.com/PackeTsar/autoshell
Author: John W Kerns
Author-email: jkerns@packetsar.com
License: GNU
Classifier: Development Status :: 4 - Beta
Classifier: Environment :: Console
Classifier: Intended Audience :: Information Technology
Classifier: License :: OSI Approved :: GNU General Public License v3 (GPLv3)
Classifier: Natural Language :: English
Classifier: Operating System :: MacOS
Classifier: Operating System :: POSIX
Classifier: Programming Language :: Python
Classifier: Programming Language :: Python :: 3.6
Classifier: Programming Language :: Python :: 3.7
Classifier: Programming Language :: Python :: 3.8
Classifier: Programming Language :: Python :: 3.9
Classifier: Topic :: Internet
Classifier: Topic :: Utilities
Classifier: Topic :: Software Development :: Libraries :: Python Modules
Classifier: Topic :: System
Classifier: Topic :: System :: Networking
License-File: LICENSE
Requires-Dist: future
Requires-Dist: pyyaml
Requires-Dist: netmiko
Requires-Dist: jinja2
